datalib/__init__.py
datalib/advanced_analysis.py
datalib/data_processing.py
datalib/statistics.py
datalib/visualization.py
FatmaBouzgarrou_DATALIB-0.1.0.dist-info/METADATA
FatmaBouzgarrou_DATALIB-0.1.0.dist-info/WHEEL
FatmaBouzgarrou_DATALIB-0.1.0.dist-info/top_level.txt
FatmaBouzgarrou_DATALIB-0.1.0.dist-info/RECORD
